ai_dashboard/__init__.py
ai_dashboard/constants.py
ai_dashboard/errors.py
ai_dashboard/types.py
ai_dashboard/api/__init__.py
ai_dashboard/api/client.py
ai_dashboard/api/endpoints.py
ai_dashboard/api/helpers.py
ai_dashboard/dashboard/__init__.py
ai_dashboard/dashboard/dashboard.py
ai_dashboard/tabs/__init__.py
ai_dashboard/tabs/abstract_tab.py
ai_dashboard/tabs/category_view.py
ai_dashboard/tabs/chart_view.py
ai_dashboard/tabs/document_view.py
ai_dashboard/tabs/data_report/__init__.py
ai_dashboard/tabs/data_report/aggregation_chart.py
ai_dashboard/tabs/data_report/constants.py
ai_dashboard/tabs/data_report/data_report.py
ai_dashboard/tabs/data_report/markdown.py
ai_dashboard/tabs/data_report/metric.py
src/__init__.py
tests/__init__.py
RelevanceAI_Explore_App_SDK-0.0.7.dist-info/LICENSE
RelevanceAI_Explore_App_SDK-0.0.7.dist-info/METADATA
RelevanceAI_Explore_App_SDK-0.0.7.dist-info/WHEEL
RelevanceAI_Explore_App_SDK-0.0.7.dist-info/top_level.txt
RelevanceAI_Explore_App_SDK-0.0.7.dist-info/RECORD
