Metadata-Version: 2.1
Name: RelevanceAI-Explore-App-SDK
Version: 0.0.7
Home-page: https://relevance.ai/
Author: Relevance AI
Author-email: dev@relevance.ai
License-File: LICENSE
Requires-Dist: marko (==1.2.2)
Requires-Dist: requests (>=2.0.0)
Provides-Extra: tests
Requires-Dist: pytest ; extra == 'tests'
Requires-Dist: pytest-xdist ; extra == 'tests'
Requires-Dist: pytest-cov ; extra == 'tests'
